nikohomecontrol/__init__.py
nikohomecontrol/nhcconnection.py
nikohomecontrol/nhcdiscover.py
nikohomecontrol/nhcmonitor.py
nikohomecontrol/nikohomecontrol.py
niko_home_control-0.3.0.dist-info/LICENSE
niko_home_control-0.3.0.dist-info/METADATA
niko_home_control-0.3.0.dist-info/WHEEL
niko_home_control-0.3.0.dist-info/top_level.txt
niko_home_control-0.3.0.dist-info/RECORD
